risca.v
module risca (
    input  wire        clk,
    input  wire        rst_n,
    output wire [31:0] imem_addr,
    input  wire [15:0] imem_data,
    output wire [31:0] dmem_addr,
    output wire [31:0] dmem_wdata,
    input  wire [31:0] dmem_rdata,
    output wire        dmem_we,
    output wire [3:0]  dmem_sel
);
    // debug only !!! remove
    // Для отладки в GTKWave - отдельные сигналы для каждого регистра
    wire [31:0] r0, r1, r2, r3, r4, r5, r6, r7;
    wire [31:0] r8, r9, r10, r11, r12, r13, r14, r15;
    assign r0  = regfile[0];
    assign r1  = regfile[1];
    assign r2  = regfile[2];
    assign r3  = regfile[3];
    assign r4  = regfile[4];
    assign r5  = regfile[5];
    assign r6  = regfile[6];
    assign r7  = regfile[7];
    assign r8  = regfile[8];
    assign r9  = regfile[9];
    assign r10 = regfile[10];
    assign r11 = regfile[11];
    assign r12 = regfile[12];
    assign r13 = regfile[13];
    assign r14 = regfile[14];
    assign r15 = regfile[15];
    // end debug only

    // opcodes
    localparam OP_ALU_RR   = 3'd0;
    localparam OP_ALU_RI   = 3'd1;
    localparam OP_MOV_RI    = 3'd2;
    localparam OP_ST_LD    = 3'd3;
    localparam OP_BRANCH   = 3'd4;
    localparam OP_LDI      = 3'd5;
    localparam OP_CALL_RET = 3'd6;
    localparam OP_INT      = 3'd7;

    // ALU
    localparam ALU_MOV   = 4'd0;
    localparam ALU_ADD   = 4'd1;
    localparam ALU_SUB   = 4'd2;
    localparam ALU_AND   = 4'd3;
    localparam ALU_OR    = 4'd4;
    localparam ALU_XOR   = 4'd5;
    localparam ALU_NOT   = 4'd6;
    localparam ALU_MUL   = 4'd7;
    localparam ALU_SLT   = 4'd8;
    localparam ALU_SLTU  = 4'd9;
    localparam ALU_SHL   = 4'd10;
    localparam ALU_SHR   = 4'd11;
    localparam ALU_MOVI   = 4'd12;
    localparam ALU_MOVL   = 4'd13;

    // MOVI and MOVH
    localparam MOVI_MOV  = 3'd0;
    localparam MOVL_MOV  = 3'd1;

    // ALU IMM 
    localparam ALU_SHLI   = 2'd0;
    localparam ALU_SHRI   = 2'd1;
    localparam ALU_ADDI  = 2'd2;
    localparam ALU_SUBI  = 2'd3;

    reg [31:0] pc;
    reg [31:0] regfile [0:15];
    integer _i;
    initial for (_i = 0; _i < 16; _i = _i + 1) regfile[_i] = 32'b0;

    assign imem_addr = pc;

    // debug only !!! remove
    reg [15:0] id_instr;
    reg [15:0] ex_instr;
    reg [15:0] mem_instr;
    reg [15:0] wb_instr;
    // end debug only


    // IF stage ----------------------------------------------------------
    reg [15:0] if_instr;

    always @(posedge clk or negedge rst_n) begin
        if (!rst_n) begin
            pc <= 32'h0;
            if_instr <= 16'h0000;
        end
        else begin
            pc <= pc + 2;
            if_instr <= imem_data;
        end
    end

    // ID stage ----------------------------------------------------------
    wire [2:0]  i_opcode = if_instr[2:0];
    wire [3:0]  i_rd     = if_instr[6:3];
    wire [3:0]  i_rs     = if_instr[10:7];
    wire [3:0]  i_func4  = if_instr[14:11];
    wire [1:0]  i_func2  = if_instr[8:7];
    wire        i_func1  = if_instr[7];
    wire [7:0]  i_imm8   = if_instr[15:8];
    wire [6:0]  i_imm7   = if_instr[15:9];
    
    reg [2:0] id_opcode;
    reg [3:0] id_rs;
    reg [3:0] id_rd;
    reg [2:0] id_func4;

    reg [31:0] id_alu_in_a;
    reg [31:0] id_alu_in_b;
    reg [3:0]  id_alu_op;
    
    always @(posedge clk or negedge rst_n) begin
        if (!rst_n) begin
            id_opcode <= 3'd0;
            id_rs <= 4'd0;
            id_rd <= 4'd0;
            id_func4 <= 3'd0;
            id_alu_in_a <= 32'd0;
            id_alu_in_b <= 32'd0;
            id_alu_op <= 3'd0;
            id_instr <= 16'd0; //debug
        end
        else begin
            id_opcode <= i_opcode;
            id_rs <= i_rs;
            id_rd <= i_rd;
            id_func4 <= i_func4;
            id_alu_in_a <= 32'd0;
            id_alu_in_b <= 32'd0;
            id_instr <= if_instr; //debug
            case (i_opcode)
                OP_ALU_RR: begin
                    id_alu_in_a <= regfile[i_rd];
                    id_alu_in_b <= regfile[i_rs];
                    id_alu_op <= i_func4;
                end
                OP_ALU_RI: begin
                    id_alu_in_a <= regfile[i_rd];
                    id_alu_in_b <= {{24{i_imm7[6]}}, i_imm7};
                    id_alu_op <= i_func4;
                    case (i_func2) 
                        ALU_SHLI: id_alu_op <= ALU_SHL;
                        ALU_SHRI: id_alu_op <= ALU_SHR;
                        ALU_ADDI: id_alu_op <= ALU_ADD;
                        ALU_SUBI: id_alu_op <= ALU_SUB;
                    endcase
                end
                OP_MOV_RI: begin
                    id_alu_in_a <= regfile[i_rd];
                    id_alu_in_b <= {{24{i_imm8[7]}}, i_imm8}; // sign-extend immediate
                    case (i_func1)
                        MOVI_MOV: id_alu_op <= ALU_MOVI;
                        MOVL_MOV: id_alu_op <= ALU_MOVL;
                    endcase
                end
            endcase
        end
    end

    // EX stage ----------------------------------------------------------
    reg [31:0] ex_alu_out;
    reg [3:0]  ex_rd;
    reg [2:0]  ex_opcode;

    wire [31:0] fwd_in_a;
    wire [31:0] fwd_in_b;

    // Forwarding logic
    wire is_src_a_valid = (id_opcode == OP_ALU_RR) || (id_opcode == OP_ALU_RI) || (id_opcode == OP_MOV_RI);
    wire is_src_b_valid = (id_opcode == OP_ALU_RR);

    assign fwd_in_a = (is_src_a_valid && (id_rd == ex_rd)) ? ex_alu_out :
                      (is_src_a_valid && (id_rd == mem_rd)) ? mem_data_out :
                      id_alu_in_a;
    assign fwd_in_b = (is_src_b_valid && (id_rs == ex_rd) && (ex_rd != 0)) ? ex_alu_out :
                      (is_src_b_valid && (id_rs == mem_rd) && (mem_rd != 0)) ? mem_data_out :
                      id_alu_in_b;

    always @(posedge clk or negedge rst_n) begin
        if (!rst_n) begin
            ex_alu_out <= 32'd0;
            ex_rd <= 4'd0;
            ex_instr <= 16'd0; //debug
            ex_opcode <= 3'd0;
        end
        else begin
            ex_instr <= id_instr; //debug
            case (id_alu_op)
                ALU_MOV: ex_alu_out <= fwd_in_b;
                ALU_ADD: ex_alu_out <= fwd_in_a + fwd_in_b;
                ALU_SUB: ex_alu_out <= fwd_in_a - fwd_in_b;
                ALU_AND: ex_alu_out <= fwd_in_a & fwd_in_b;
                ALU_OR:  ex_alu_out <= fwd_in_a | fwd_in_b;
                ALU_XOR: ex_alu_out <= fwd_in_a ^ fwd_in_b;
                ALU_NOT: ex_alu_out <= ~fwd_in_b;
                ALU_MUL: ex_alu_out <= fwd_in_a * fwd_in_b;
                ALU_SLT: ex_alu_out <= ($signed(fwd_in_a) < $signed(fwd_in_b)) ? 32'd1 : 32'd0;
                ALU_SLTU: ex_alu_out <= (fwd_in_a < fwd_in_b) ? 32'd1 : 32'd0;
                ALU_SHL: ex_alu_out <= fwd_in_a << fwd_in_b[4:0];
                ALU_SHR: ex_alu_out <= fwd_in_a >> fwd_in_b[4:0];
                ALU_MOVI: ex_alu_out <= fwd_in_b;
                ALU_MOVL: ex_alu_out <= {fwd_in_a[23:0], fwd_in_b[7:0]}; // shift left 8 bits and insert immediate
            endcase
            ex_rd <= id_rd;
            ex_opcode <= id_opcode;
        end
    end

    // MEM stage ----------------------------------------------------------
    reg [31:0] mem_data_out;
    reg [3:0]  mem_rd;
    reg [2:0]  mem_opcode;

    always @(posedge clk or negedge rst_n) begin
        if (!rst_n) begin
            mem_data_out <= 32'd0;
            mem_rd <= 4'd0;
            mem_opcode <= 3'd0;
            mem_instr <= 16'd0; //debug
        end
        else begin
            mem_instr <= ex_instr; //debug
            case (ex_opcode)
                OP_ALU_RR: mem_data_out <= ex_alu_out;
                OP_ALU_RI: mem_data_out <= ex_alu_out;
                OP_MOV_RI: mem_data_out <= ex_alu_out;
            endcase
            mem_rd <= ex_rd;
            mem_opcode <= ex_opcode;
        end
    end

    // WB stage  ----------------------------------------------------------
    always @(posedge clk  or negedge rst_n) begin
        if (!rst_n) begin
            wb_instr <= 16'd0;
        end
        else begin
            wb_instr <= mem_instr;
            case (mem_opcode)
                OP_ALU_RR: regfile[mem_rd] <= mem_data_out;
                OP_ALU_RI: regfile[mem_rd] <= mem_data_out;
                OP_MOV_RI: regfile[mem_rd] <= mem_data_out;
            endcase
        end
    end

endmodule

risca_tb.v
`timescale 1ns/1ps

`define MOVI(rd, imm)  (((imm) << 8) | (1'b0 << 7) | ((rd) << 3) | 3'b010)
`define MOVL(rd, imm)  (((imm) << 8) | (1'b1 << 7) | ((rd) << 3) | 3'b010)
`define MOV(rd, rs)    ((4'b0000 << 11) | ((rs) << 7) | ((rd) << 3) | 3'b000)
`define ADD(rd, rs)    ((4'b0001 << 11) | ((rs) << 7) | ((rd) << 3) | 3'b000)
`define SUB(rd, rs)    ((4'b0010 << 11) | ((rs) << 7) | ((rd) << 3) | 3'b000)
`define AND(rd, rs)    ((4'b0011 << 11) | ((rs) << 7) | ((rd) << 3) | 3'b000)
`define OR(rd, rs)     ((4'b0100 << 11) | ((rs) << 7) | ((rd) << 3) | 3'b000)
`define XOR(rd, rs)    ((4'b0101 << 11) | ((rs) << 7) | ((rd) << 3) | 3'b000)
`define NOT(rd, rs)    ((4'b0110 << 11) | ((rs) << 7) | ((rd) << 3) | 3'b000)
`define MUL(rd, rs)    ((4'b0111 << 11) | ((rs) << 7) | ((rd) << 3) | 3'b000)
`define SLT(rd, rs)    ((4'b1000 << 11) | ((rs) << 7) | ((rd) << 3) | 3'b000)
`define SLTU(rd, rs)   ((4'b1001 << 11) | ((rs) << 7) | ((rd) << 3) | 3'b000)
`define ADDI(rd, imm)  (((imm) << 9) | (2'b10 << 7) | ((rd) << 3) | 3'b001)
`define SUBI(rd, imm)  (((imm) << 9) | (2'b11 << 7) | ((rd) << 3) | 3'b001)
`define SHL(rd, imm)   (((imm) << 9) | (2'b00 << 7) | ((rd) << 3) | 3'b001)
`define SHR(rd, imm)   (((imm) << 9) | (2'b01 << 7) | ((rd) << 3) | 3'b001)
`define LDW(rd, rs, imm) (((imm) << 13) | (1'b1 << 12) | (1'b0 << 11) | ((rs) << 7) | ((rd) << 3) | 3'b011)
`define STW(rd, rs, imm) (((imm) << 13) | (1'b1 << 12) | (1'b1 << 11) | ((rs) << 7) | ((rd) << 3) | 3'b011)
`define LDB(rd, rs, imm) (((imm) << 13) | (1'b0 << 12) | (1'b0 << 11) | ((rs) << 7) | ((rd) << 3) | 3'b011)
`define STB(rd, rs, imm) (((imm) << 13) | (1'b0 << 12) | (1'b1 << 11) | ((rs) << 7) | ((rd) << 3) | 3'b011)
`define BEQZ(rd, imm)  (((imm) << 8) | (1'b0 << 7) | ((rd) << 3) | 3'b100)
`define BNEZ(rd, imm)  (((imm) << 8) | (1'b1 << 7) | ((rd) << 3) | 3'b100)
`define CALLI(rd, imm) (((imm) << 9) | (2'b00 << 7) | ((rd) << 3) | 3'b110)
`define CALLR(rd)      ((2'b01 << 7) | ((rd) << 3) | 3'b110)
`define RET(rd)        ((2'b10 << 7) | ((rd) << 3) | 3'b110)
`define JR(rd, imm)    (((imm) << 9) | (2'b11 << 7) | ((rd) << 3) | 3'b110)
`define NOP            16'h0000

module risca_tb;

    reg         clk;
    reg         rst_n;

    reg  [15:0] imem [0:1023];
    wire [31:0] imem_addr;
    wire [15:0] imem_data;

    reg  [31:0] dmem [0:1023];
    wire [31:0] dmem_addr;
    wire [31:0] dmem_wdata;
    wire [31:0] dmem_rdata;
    wire        dmem_we;
    wire [3:0]  dmem_sel;

    wire [31:0] pc_debug;

    assign imem_data = imem[imem_addr[31:1]];
    assign dmem_rdata = dmem[dmem_addr[31:2]];

    risca cpu (
        .clk        (clk),
        .rst_n      (rst_n),
        .imem_addr  (imem_addr),
        .imem_data  (imem_data),
        .dmem_addr  (dmem_addr),
        .dmem_wdata (dmem_wdata),
        .dmem_rdata (dmem_rdata),
        .dmem_we    (dmem_we),
        .dmem_sel   (dmem_sel)
    );

    always #5 clk = ~clk;

    always @(posedge clk) begin
        if (dmem_we) begin
            if (dmem_sel[0]) dmem[dmem_addr[31:2]][7:0]   <= dmem_wdata[7:0];
            if (dmem_sel[1]) dmem[dmem_addr[31:2]][15:8]  <= dmem_wdata[15:8];
            if (dmem_sel[2]) dmem[dmem_addr[31:2]][23:16] <= dmem_wdata[23:16];
            if (dmem_sel[3]) dmem[dmem_addr[31:2]][31:24] <= dmem_wdata[31:24];
        end
    end

    initial begin
        $dumpfile("risca_tb.vcd");
        $dumpvars(0, risca_tb);

        imem[0]  = `MOVI(1, 10); $display(" imem[0] = %h", imem[0]);      // 0x00: R1 = 10
        imem[1]  = `MOVI(2, 20); $display(" imem[1] = %h", imem[1]);      // 0x02: R2 = 20
        imem[2]  = `MOV(3, 1); $display(" imem[2] = %h", imem[2]);        // 0x04: R3 = R1 = 10
        imem[3]  = `ADD(3, 2); $display(" imem[3] = %h", imem[3]);        // 0x06: R3 = 10 + 20 = 30
        imem[4]  = `MOV(4, 3); $display(" imem[4] = %h", imem[4]);        // 0x08: R4 = R3 = 30
        imem[5]  = `SUB(4, 2); $display(" imem[5] = %h", imem[5]);        // 0x0A: R4 = 30 - 20 = 10
        imem[6]  = `MOV(5, 4); $display(" imem[6] = %h", imem[6]);        // 0x0C: R5 = R4 = 10
        imem[7]  = `SHL(5, 1); $display(" imem[7] = %h", imem[7]);        // 0x0E: R5 = 10 << 1 = 20
        imem[8]  = `ADDI(5, 2); $display(" imem[8] = %h", imem[8]);        // 0x10: R5 = 20 + 2 = 22
        imem[9]  = `MOVL(5, 255); $display(" imem[9] = %h", imem[9]);        // 0x12: R5 = (22 << 8) + 255 = 5887
        imem[10]  = `MOV(6, 4); $display(" imem[10] = %h", imem[10]);        // 0x0C: R6 = R4 = 10
        imem[11]  = `SLTU(6, 5); $display(" imem[11] = %h", imem[11]);        // 0x0E: R6 = R6 < R5 = 10 < 5887 = 1


        clk = 0;
        rst_n = 0;
        #15 rst_n = 1;

        #600;

        $display("--- Simulation complete ---");
        $display("R1  = %0d (expected 10)",  cpu.regfile[1]);
        $display("R2  = %0d (expected 20)",  cpu.regfile[2]);
        $display("R3  = %0d (expected 30)",  cpu.regfile[3]);
        $display("R4  = %0d (expected 10)",  cpu.regfile[4]);
        $display("R5  = %0d (expected 5887)",  cpu.regfile[5]);
        $display("R6  = %0d (expected 1)",   cpu.regfile[6]);
        if (cpu.regfile[1] == 10 && cpu.regfile[2] == 20 &&
            cpu.regfile[3] == 30 && cpu.regfile[4] == 10 && 
            cpu.regfile[5] == 5887 && cpu.regfile[6] == 1)
            $display("*** TEST PASSED ***");
        else
            $display("*** TEST FAILED ***");

        $finish;
    end

endmodule

risca_tb.vcd
$date
	Thu Jul 23 21:28:02 2026
$end
$version
	Icarus Verilog
$end
$timescale
	1ps
$end
$scope module risca_tb $end
$var wire 32 ! dmem_addr [31:0] $end
$var wire 32 " dmem_rdata [31:0] $end
$var wire 4 # dmem_sel [3:0] $end
$var wire 32 $ dmem_wdata [31:0] $end
$var wire 1 % dmem_we $end
$var wire 16 & imem_data [15:0] $end
$var wire 32 ' imem_addr [31:0] $end
$var reg 1 ( clk $end
$var reg 1 ) rst_n $end
$scope module cpu $end
$var wire 1 ( clk $end
$var wire 32 * dmem_addr [31:0] $end
$var wire 32 + dmem_rdata [31:0] $end
$var wire 4 , dmem_sel [3:0] $end
$var wire 32 - dmem_wdata [31:0] $end
$var wire 1 % dmem_we $end
$var wire 16 . imem_data [15:0] $end
$var wire 1 / is_src_a_valid $end
$var wire 32 0 r0 [31:0] $end
$var wire 32 1 r1 [31:0] $end
$var wire 32 2 r10 [31:0] $end
$var wire 32 3 r11 [31:0] $end
$var wire 32 4 r12 [31:0] $end
$var wire 32 5 r13 [31:0] $end
$var wire 32 6 r14 [31:0] $end
$var wire 32 7 r15 [31:0] $end
$var wire 32 8 r2 [31:0] $end
$var wire 32 9 r3 [31:0] $end
$var wire 32 : r4 [31:0] $end
$var wire 32 ; r5 [31:0] $end
$var wire 32 < r6 [31:0] $end
$var wire 32 = r7 [31:0] $end
$var wire 32 > r8 [31:0] $end
$var wire 32 ? r9 [31:0] $end
$var wire 1 ) rst_n $end
$var wire 1 @ is_src_b_valid $end
$var wire 32 A imem_addr [31:0] $end
$var wire 4 B i_rs [3:0] $end
$var wire 4 C i_rd [3:0] $end
$var wire 3 D i_opcode [2:0] $end
$var wire 8 E i_imm8 [7:0] $end
$var wire 7 F i_imm7 [6:0] $end
$var wire 4 G i_func4 [3:0] $end
$var wire 2 H i_func2 [1:0] $end
$var wire 1 I i_func1 $end
$var wire 32 J fwd_in_b [31:0] $end
$var wire 32 K fwd_in_a [31:0] $end
$var parameter 4 L ALU_ADD $end
$var parameter 2 M ALU_ADDI $end
$var parameter 4 N ALU_AND $end
$var parameter 4 O ALU_MOV $end
$var parameter 4 P ALU_MOVI $end
$var parameter 4 Q ALU_MOVL $end
$var parameter 4 R ALU_MUL $end
$var parameter 4 S ALU_NOT $end
$var parameter 4 T ALU_OR $end
$var parameter 4 U ALU_SHL $end
$var parameter 2 V ALU_SHLI $end
$var parameter 4 W ALU_SHR $end
$var parameter 2 X ALU_SHRI $end
$var parameter 4 Y ALU_SLT $end
$var parameter 4 Z ALU_SLTU $end
$var parameter 4 [ ALU_SUB $end
$var parameter 2 \ ALU_SUBI $end
$var parameter 4 ] ALU_XOR $end
$var parameter 3 ^ MOVI_MOV $end
$var parameter 3 _ MOVL_MOV $end
$var parameter 3 ` OP_ALU_RI $end
$var parameter 3 a OP_ALU_RR $end
$var parameter 3 b OP_BRANCH $end
$var parameter 3 c OP_CALL_RET $end
$var parameter 3 d OP_INT $end
$var parameter 3 e OP_LDI $end
$var parameter 3 f OP_MOV_RI $end
$var parameter 3 g OP_ST_LD $end
$var reg 32 h ex_alu_out [31:0] $end
$var reg 16 i ex_instr [15:0] $end
$var reg 3 j ex_opcode [2:0] $end
$var reg 4 k ex_rd [3:0] $end
$var reg 32 l id_alu_in_a [31:0] $end
$var reg 32 m id_alu_in_b [31:0] $end
$var reg 4 n id_alu_op [3:0] $end
$var reg 3 o id_func4 [2:0] $end
$var reg 16 p id_instr [15:0] $end
$var reg 3 q id_opcode [2:0] $end
$var reg 4 r id_rd [3:0] $end
$var reg 4 s id_rs [3:0] $end
$var reg 16 t if_instr [15:0] $end
$var reg 32 u mem_data_out [31:0] $end
$var reg 16 v mem_instr [15:0] $end
$var reg 3 w mem_opcode [2:0] $end
$var reg 4 x mem_rd [3:0] $end
$var reg 32 y pc [31:0] $end
$var reg 16 z wb_instr [15:0] $end
$var integer 32 { _i [31:0] $end
$upscope $end
$upscope $end
$enddefinitions $end
$comment Show the parameter values. $end
$dumpall
b11 g
b10 f
b101 e
b111 d
b110 c
b100 b
b0 a
b1 `
b1 _
b0 ^
b101 ]
b11 \
b10 [
b1001 Z
b1000 Y
b1 X
b1011 W
b0 V
b1010 U
b100 T
b110 S
b111 R
b1101 Q
b1100 P
b0 O
b11 N
b10 M
b1 L
$end
#0
$dumpvars
b10000 {
b0 z
b0 y
b0 x
b0 w
b0 v
b0 u
b0 t
b0 s
b0 r
b0 q
b0 p
b0 o
b0 n
b0 m
b0 l
b0 k
b0 j
b0 i
b0 h
b0 K
b0 J
0I
b0 H
b0 G
b0 F
b0 E
b0 D
b0 C
b0 B
b0 A
1@
b0 ?
b0 >
b0 =
b0 <
b0 ;
b0 :
b0 9
b0 8
b0 7
b0 6
b0 5
b0 4
b0 3
b0 2
b0 1
b0 0
1/
b101000001010 .
bz -
bz ,
bx +
bz *
0)
0(
b0 '
b101000001010 &
z%
bz $
bz #
bx "
bz !
$end
#5000
1(
#10000
0(
#15000
b10 D
b1 C
b100 B
b1 G
b1010 E
b101 F
b1010000010010 &
b1010000010010 .
b101000001010 t
b10 '
b10 A
b10 y
1(
1)
#20000
0(
#25000
b1010 J
b10 C
b1000 B
b10 G
b10100 E
b1010 F
b10011000 &
b10011000 .
b1100 n
b1010 m
b101000001010 p
b1 o
b1 r
b100 s
0@
b10 q
b1010000010010 t
b100 '
b100 A
b100 y
1(
#30000
0(
#35000
b10100 J
b0 D
b11 C
b1 B
b0 G
b1 H
1I
b0 E
b0 F
b100100011000 &
b100100011000 .
b10011000 t
b110 '
b110 A
b110 y
b1010000010010 p
b10100 m
b10 o
b10 r
b1000 s
b10 j
b1 k
b1010 h
b101000001010 i
1(
#40000
0(
#45000
b1010 J
1/
b10 B
b1 G
b10 H
0I
b1001 E
b100 F
b110100000 &
b110100000 .
b10 w
b1 x
b1010 u
b101000001010 v
b10 k
b10100 h
b1010000010010 i
b0 n
b10011000 p
b0 m
b0 o
b11 r
b1 s
1@
b0 q
b100100011000 t
b1000 '
b1000 A
b1000 y
1(
#50000
0(
#55000
b1010 K
b10100 J
b100 C
b11 B
b0 G
b11 H
1I
b1 E
b0 F
b1000100100000 &
b1000100100000 .
b110100000 t
b1010 '
b1010 A
b1010 y
b1 n
b100100011000 p
b1 o
b10 s
b0 j
b11 k
b1010 h
b10011000 i
b10 x
b10100 u
b1010000010010 v
b1010 1
b101000001010 z
1(
#60000
0(
#65000
b11110 J
b0 K
b10 B
b10 G
b10 H
0I
b10001 E
b1000 F
b1000101000 &
b1000101000 .
b10100 8
b1010000010010 z
b0 w
b11 x
b1010 u
b10011000 v
b11110 h
b100100011000 i
b0 n
b110100000 p
b0 o
b100 r
b11 s
b1000100100000 t
b1100 '
b1100 A
b1100 y
1(
#70000
0(
#75000
b10100 J
b11110 K
b101 C
b100 B
b0 G
b0 H
b10 E
b1 F
b1000101001 &
b1000101001 .
b1000101000 t
b1110 '
b1110 A
b1110 y
b10 n
b10100 m
b1000100100000 p
b10 o
b10 s
b100 k
b110100000 i
b11110 u
b100100011000 v
b1010 9
b10011000 z
1(
#80000
0(
#85000
b1010 J
b0 K
b1 D
b10100101001 &
b10100101001 .
b11110 9
b100100011000 z
b100 x
b110100000 v
b1010 h
b1000100100000 i
b0 n
b1000101000 p
b0 m
b0 o
b101 r
b100 s
b1000101001 t
b10000 '
b10000 A
b10000 y
1(
#90000
0(
#95000
b1 J
b1010 K
b1010 B
b10 H
b101 E
b10 F
b1111111110101010 &
b1111111110101010 .
b10100101001 t
b10010 '
b10010 A
b10010 y
b1010 n
b1 m
b1000101001 p
0@
b1 q
b101 k
b1000101000 i
b1010 u
b1000100100000 v
b11110 :
b110100000 z
1(
#100000
0(
#105000
b10 J
b10100 K
b10 D
b1111 B
b1111 G
b11 H
1I
b11111111 E
b1111111 F
b1000110000 &
b1000110000 .
b1010 :
b1000100100000 z
b101 x
b1000101000 v
b1 j
b10100 h
b1000101001 i
b1 n
b10100101001 p
b10 m
b1010 s
b1111111110101010 t
b10100 '
b10100 A
b10100 y
1(
#110000
0(
#115000
b11111111111111111111111111111111 J
b0 D
b110 C
b100 B
b0 G
b0 H
0I
b10 E
b1 F
b100101010110000 &
b100101010110000 .
b10110 K
b1000110000 t
b10110 '
b10110 A
b10110 y
b1101 n
b1111111110101010 p
b11111111111111111111111111111111 m
b111 o
b1111 s
b10 q
b10110 h
b10100101001 i
b1 w
b10100 u
b1000101001 v
b1010 ;
b1000101000 z
1(
#120000
0(
#125000
b1010 J
b0 K
1/
b101 B
b1001 G
b1 H
1I
b1001010 E
b100101 F
bx &
bx .
b10100 ;
b1000101001 z
b10110 u
b10100101001 v
b10 j
b1011011111111 h
b1111111110101010 i
b0 n
b1000110000 p
b1010 m
b0 o
b110 r
b100 s
1@
b0 q
b100101010110000 t
b11000 '
b11000 A
b11000 y
1(
#130000
0(
#135000
b1011011111111 J
b1010 K
bx D
bx C
bx B
bx G
bx H
xI
bx E
bx F
bx t
b11010 '
b11010 A
b11010 y
b1001 n
b100101010110000 p
b10100 m
b1 o
b101 s
b0 j
b110 k
b1010 h
b1000110000 i
b10 w
b1011011111111 u
b1111111110101010 v
b10110 ;
b10100101001 z
1(
#140000
0(
#145000
b0x0xx J
x/
b0x0xx K
b1011011111111 ;
b1111111110101010 z
b0 w
b110 x
b1010 u
b1000110000 v
b1 h
b100101010110000 i
bx p
b0 m
bx o
bx r
bx s
x@
bx q
b11100 '
b11100 A
b11100 y
1(
#150000
0(
#155000
b0x K
b0x J
b11110 '
b11110 A
b11110 y
bx j
bx k
b0x h
bx i
b1 u
b100101010110000 v
b1010 <
b1000110000 z
1(
#160000
0(
#165000
b1 <
b100101010110000 z
bx w
bx x
bx v
b100000 '
b100000 A
b100000 y
1(
#170000
0(
#175000
b100010 '
b100010 A
b100010 y
bx z
1(
#180000
0(
#185000
b100100 '
b100100 A
b100100 y
1(
#190000
0(
#195000
b100110 '
b100110 A
b100110 y
1(
#200000
0(
#205000
b101000 '
b101000 A
b101000 y
1(
#210000
0(
#215000
b101010 '
b101010 A
b101010 y
1(
#220000
0(
#225000
b101100 '
b101100 A
b101100 y
1(
#230000
0(
#235000
b101110 '
b101110 A
b101110 y
1(
#240000
0(
#245000
b110000 '
b110000 A
b110000 y
1(
#250000
0(
#255000
b110010 '
b110010 A
b110010 y
1(
#260000
0(
#265000
b110100 '
b110100 A
b110100 y
1(
#270000
0(
#275000
b110110 '
b110110 A
b110110 y
1(
#280000
0(
#285000
b111000 '
b111000 A
b111000 y
1(
#290000
0(
#295000
b111010 '
b111010 A
b111010 y
1(
#300000
0(
#305000
b111100 '
b111100 A
b111100 y
1(
#310000
0(
#315000
b111110 '
b111110 A
b111110 y
1(
#320000
0(
#325000
b1000000 '
b1000000 A
b1000000 y
1(
#330000
0(
#335000
b1000010 '
b1000010 A
b1000010 y
1(
#340000
0(
#345000
b1000100 '
b1000100 A
b1000100 y
1(
#350000
0(
#355000
b1000110 '
b1000110 A
b1000110 y
1(
#360000
0(
#365000
b1001000 '
b1001000 A
b1001000 y
1(
#370000
0(
#375000
b1001010 '
b1001010 A
b1001010 y
1(
#380000
0(
#385000
b1001100 '
b1001100 A
b1001100 y
1(
#390000
0(
#395000
b1001110 '
b1001110 A
b1001110 y
1(
#400000
0(
#405000
b1010000 '
b1010000 A
b1010000 y
1(
#410000
0(
#415000
b1010010 '
b1010010 A
b1010010 y
1(
#420000
0(
#425000
b1010100 '
b1010100 A
b1010100 y
1(
#430000
0(
#435000
b1010110 '
b1010110 A
b1010110 y
1(
#440000
0(
#445000
b1011000 '
b1011000 A
b1011000 y
1(
#450000
0(
#455000
b1011010 '
b1011010 A
b1011010 y
1(
#460000
0(
#465000
b1011100 '
b1011100 A
b1011100 y
1(
#470000
0(
#475000
b1011110 '
b1011110 A
b1011110 y
1(
#480000
0(
#485000
b1100000 '
b1100000 A
b1100000 y
1(
#490000
0(
#495000
b1100010 '
b1100010 A
b1100010 y
1(
#500000
0(
#505000
b1100100 '
b1100100 A
b1100100 y
1(
#510000
0(
#515000
b1100110 '
b1100110 A
b1100110 y
1(
#520000
0(
#525000
b1101000 '
b1101000 A
b1101000 y
1(
#530000
0(
#535000
b1101010 '
b1101010 A
b1101010 y
1(
#540000
0(
#545000
b1101100 '
b1101100 A
b1101100 y
1(
#550000
0(
#555000
b1101110 '
b1101110 A
b1101110 y
1(
#560000
0(
#565000
b1110000 '
b1110000 A
b1110000 y
1(
#570000
0(
#575000
b1110010 '
b1110010 A
b1110010 y
1(
#580000
0(
#585000
b1110100 '
b1110100 A
b1110100 y
1(
#590000
0(
#595000
b1110110 '
b1110110 A
b1110110 y
1(
#600000
0(
#605000
b1111000 '
b1111000 A
b1111000 y
1(
#610000
0(
#615000
b1111010 '
b1111010 A
b1111010 y
1(
